pyeuler3d/E3Dbin.py
pyeuler3d/__init__.py
pyeuler3d/config.py
pyeuler3d-0.0.1.dist-info/LICENSE
pyeuler3d-0.0.1.dist-info/METADATA
pyeuler3d-0.0.1.dist-info/WHEEL
pyeuler3d-0.0.1.dist-info/top_level.txt
pyeuler3d-0.0.1.dist-info/RECORD
