Metadata-Version: 2.1
Name: pyeuler3d
Version: 0.0.1
Summary: UNKNOWN
Home-page: UNKNOWN
License: GPLv3
Platform: UNKNOWN
Requires-Dist: pytecplot
